gqlactioncable/__init__.py
gqlactioncable/__version__.py
gqlactioncable/actioncable_protocol.py
gqlactioncable/actioncable_websockets.py
gqlactioncable/py.typed
gqlactioncable-1.0.2.dist-info/licenses/LICENSE
gqlactioncable-1.0.2.dist-info/METADATA
gqlactioncable-1.0.2.dist-info/WHEEL
gqlactioncable-1.0.2.dist-info/top_level.txt
gqlactioncable-1.0.2.dist-info/RECORD
